README.rst
setup.py
django_ses_feedback/__init__.py
django_ses_feedback/apps.py
django_ses_feedback/helpers.py
django_ses_feedback/models.py
django_ses_feedback/settings.py
django_ses_feedback/signals.py
django_ses_feedback.egg-info/PKG-INFO
django_ses_feedback.egg-info/SOURCES.txt
django_ses_feedback.egg-info/dependency_links.txt
django_ses_feedback.egg-info/requires.txt
django_ses_feedback.egg-info/top_level.txt
django_ses_feedback/migrations/0001_initial.py
django_ses_feedback/migrations/0002_alter_emailaddressnotification_notifications.py
django_ses_feedback/migrations/__init__.py