Metadata-Version: 1.1
Name: django-ses-feedback
Version: 0.2.1b0
Summary: Process Amazon SES Feedback
Home-page: https://hg.code.netlandish.com/~netlandish/django-ses-feedback/
Author: Netlandish Inc.
Author-email: hello@netlandish.com
License: UNKNOWN
Platform: any
Classifier: Development Status :: 4 - Beta
Classifier: Intended Audience :: Developers
Classifier: Natural Language :: English
Classifier: Operating System :: OS Independent
Classifier: Programming Language :: Python
Classifier: Programming Language :: Python :: 3.6
Classifier: Programming Language :: Python :: 3.7
Classifier: Programming Language :: Python :: 3.8
Classifier: Environment :: Web Environment
